representty.py
representty-0.1.5.dist-info/entry_points.txt
representty-0.1.5.dist-info/WHEEL
representty-0.1.5.dist-info/METADATA
representty-0.1.5.dist-info/RECORD
