Metadata-Version: 2.1
Name: representty
Version: 0.1.5
Summary: Tiny presentation tool based on rich and markdown
Home-page: https://github.com/L3viathan/representty
License: MIT
Keywords: presentation
Author: L3viathan
Author-email: git@l3vi.de
Requires-Python: >=3.10,<4.0
Classifier: Development Status :: 3 - Alpha
Classifier: Environment :: Console
Classifier: Framework :: IPython
Classifier: License :: OSI Approved :: MIT License
Classifier: Programming Language :: Python
Classifier: Programming Language :: Python :: 3
Classifier: Programming Language :: Python :: 3 :: Only
Classifier: Programming Language :: Python :: 3.10
Classifier: Topic :: Education
Classifier: Topic :: Multimedia :: Graphics :: Presentation
Requires-Dist: ipython
Requires-Dist: rich (>=13.3.1,<14.0.0)
Project-URL: Repository, https://github.com/L3viathan/representty
